aind_codeocean_pipeline_monitor/__init__.py
aind_codeocean_pipeline_monitor/job.py
aind_codeocean_pipeline_monitor/models.py
aind_codeocean_pipeline_monitor-0.11.1.dist-info/licenses/LICENSE
aind_codeocean_pipeline_monitor-0.11.1.dist-info/METADATA
aind_codeocean_pipeline_monitor-0.11.1.dist-info/WHEEL
aind_codeocean_pipeline_monitor-0.11.1.dist-info/top_level.txt
aind_codeocean_pipeline_monitor-0.11.1.dist-info/RECORD
