Metadata-Version: 2.4
Name: aind-codeocean-pipeline-monitor
Version: 0.11.1
Summary: Package to define and run a Code Ocean Pipeline Monitor Job
Author: Allen Institute for Neural Dynamics
License: MIT
Classifier: Programming Language :: Python :: 3
Requires-Python: >=3.9
License-File: LICENSE
Requires-Dist: pydantic>=2.0
Requires-Dist: pydantic_settings>=2.0
Requires-Dist: codeocean>=0.10.0
Provides-Extra: dev
Requires-Dist: aind-codeocean-pipeline-monitor[full]; extra == "dev"
Requires-Dist: black; extra == "dev"
Requires-Dist: coverage; extra == "dev"
Requires-Dist: flake8; extra == "dev"
Requires-Dist: interrogate; extra == "dev"
Requires-Dist: isort; extra == "dev"
Requires-Dist: Sphinx; extra == "dev"
Requires-Dist: furo; extra == "dev"
Provides-Extra: full
Requires-Dist: aind-alert-utils; extra == "full"
Requires-Dist: aind-data-schema-models>=0.3.2; extra == "full"
Requires-Dist: aind-data-access-api<2.0,>=1.9.0; extra == "full"
Dynamic: license-file
